aiida_chemshell/__init__.py
aiida_chemshell/calculations.py
aiida_chemshell/parsers.py
aiida_chemshell/utils.py
aiida_chemshell-0.1.4.dist-info/licenses/LICENSE
aiida_chemshell-0.1.4.dist-info/METADATA
aiida_chemshell-0.1.4.dist-info/WHEEL
aiida_chemshell-0.1.4.dist-info/entry_points.txt
aiida_chemshell-0.1.4.dist-info/top_level.txt
aiida_chemshell-0.1.4.dist-info/RECORD
