Metadata-Version: 2.4
Name: aiida-chemshell
Version: 0.1.4
Summary: AiiDA workflow plugin for the ChemShell chemical modelling software package
Author-email: "Dr. Benjamin T. Speake" <benjamin.speake@stfc.ac.uk>
License: BSD 3-Clause License
Project-URL: Source, https://github.com/stfc/aiida-chemshell
Keywords: aiida,workflows,chemshell
Classifier: Intended Audience :: Science/Research
Classifier: Programming Language :: Python :: 3
Classifier: Topic :: Scientific/Engineering
Classifier: Framework :: AiiDA
Classifier: Development Status :: 5 - Production/Stable
Requires-Python: >=3.10
License-File: LICENSE
Requires-Dist: aiida-core>=2.5
Provides-Extra: dev
Requires-Dist: aiida-core>=2.6; extra == "dev"
Requires-Dist: pytest>=8.0; extra == "dev"
Requires-Dist: pytest-cov>=6.0; extra == "dev"
Requires-Dist: ruff>=0.11.0; extra == "dev"
Requires-Dist: pre-commit; extra == "dev"
Provides-Extra: docs
Requires-Dist: sphinx>=8.0.2; extra == "docs"
Requires-Dist: piccolo-theme>=0.14.0; extra == "docs"
Requires-Dist: sphinx-toolbox; extra == "docs"
Requires-Dist: numpydoc; extra == "docs"
Dynamic: license-file
